{
    "author": "Alessandro Stigliani",
    "authorURL": "https://unsplash.com/@nxalessandro?utm_source=Variety+Wallpaper+Changer&utm_medium=referral",
    "description": null,
    "extraData": {
        "unsplashDownloadLocation": "https://api.unsplash.com/photos/v_DGrJ5ions/download?ixid=M3wxMjIxfDB8MXxyYW5kb218fHx8fHx8fHwxNzE3OTQzMTUwfA",
        "unsplashDownloadReported": false
    },
    "imageURL": "https://images.unsplash.com/photo-1557231091-ffc9d2844e4b?crop=entropy&cs=srgb&fm=jpg&ixid=M3wxMjIxfDB8MXxyYW5kb218fHx8fHx8fHwxNzE3OTQzMTUwfA&ixlib=rb-4.0.3&q=85&w=2707",
    "keywords": [],
    "sfwRating": 100,
    "sourceLocation": "https://unsplash.com",
    "sourceName": "Unsplash.com",
    "sourceType": "unsplash",
    "sourceURL": "https://unsplash.com/photos/urban-photo-of-a-highway-v_DGrJ5ions?utm_source=Variety+Wallpaper+Changer&utm_medium=referral"
}