{
    "author": "Ian Valerio",
    "authorURL": "https://unsplash.com/@iangvalerio?utm_source=Variety+Wallpaper+Changer&utm_medium=referral",
    "description": "Get up.",
    "extraData": {
        "unsplashDownloadLocation": "https://api.unsplash.com/photos/9UxW_MqBGe4/download?ixid=M3wxMjIxfDB8MXxyYW5kb218fHx8fHx8fHwxNzE3OTQyMTI2fA",
        "unsplashDownloadReported": false
    },
    "imageURL": "https://images.unsplash.com/photo-1521022649550-47f2685cb297?crop=entropy&cs=srgb&fm=jpg&ixid=M3wxMjIxfDB8MXxyYW5kb218fHx8fHx8fHwxNzE3OTQyMTI2fA&ixlib=rb-4.0.3&q=85&w=2707",
    "keywords": [],
    "sfwRating": 100,
    "sourceLocation": "https://unsplash.com",
    "sourceName": "Unsplash.com",
    "sourceType": "unsplash",
    "sourceURL": "https://unsplash.com/photos/grey-bicycle-on-road-near-black-vehicle-at-nighttime-9UxW_MqBGe4?utm_source=Variety+Wallpaper+Changer&utm_medium=referral"
}